ordinalgbt/__init__.py
ordinalgbt/data.py
ordinalgbt/lgb.py
ordinalgbt/loss.py
ordinalgbt-0.1.2.dist-info/LICENSE
ordinalgbt-0.1.2.dist-info/METADATA
ordinalgbt-0.1.2.dist-info/WHEEL
ordinalgbt-0.1.2.dist-info/top_level.txt
ordinalgbt-0.1.2.dist-info/RECORD
