Metadata-Version: 2.1
Name: ordinalgbt
Version: 0.1.2
Summary: A library to build Gradient boosted trees for ordinal labels
Home-page: https://github.com/adamingas/ordinalgbt
Author: Adamos Spanashis
Author-email: spanashis@gmail.com
Platform: any
Classifier: Programming Language :: Python :: 3
License-File: LICENSE
Requires-Dist: lightgbm <4
Requires-Dist: numpy
Requires-Dist: scipy
Requires-Dist: scikit-learn
Provides-Extra: dev
Requires-Dist: scikit-learn ; extra == 'dev'
Requires-Dist: lightgbm <4.0.0 ; extra == 'dev'
Requires-Dist: pytest ; extra == 'dev'
Requires-Dist: pytest-cov ; extra == 'dev'
Requires-Dist: shap ; extra == 'dev'
Requires-Dist: myst-nb ; extra == 'dev'
Requires-Dist: sphinx >7.2 ; extra == 'dev'
Requires-Dist: sphinx-autoapi ; extra == 'dev'
Requires-Dist: sphinx-rtd-theme ; extra == 'dev'
Provides-Extra: tests
Requires-Dist: pytest ; extra == 'tests'
Requires-Dist: pytest-cov ; extra == 'tests'
